session_repository/__init__.py
session_repository/decorators.py
session_repository/enum.py
session_repository/utils.py
session_repository/models/repository.py
session_repository/models/service.py
session_repository-0.4.5.4.dist-info/METADATA
session_repository-0.4.5.4.dist-info/WHEEL
session_repository-0.4.5.4.dist-info/top_level.txt
session_repository-0.4.5.4.dist-info/RECORD
