Metadata-Version: 2.1
Name: session-repository
Version: 0.4.5.4
Summary: A project to have a base repository class to perform select/insert/update/delete with dynamic syntax
Home-page: https://github.com/Impro02/session-repository
Download-URL: https://github.com/Impro02/session-repository/archive/refs/tags/0.4.5.4.tar.gz
Author: Maxime MARTIN
Author-email: maxime.martin02@hotmail.fr
License: MIT
Classifier: Development Status :: 3 - Alpha
Classifier: Intended Audience :: Developers
Classifier: License :: OSI Approved :: MIT License
Classifier: Programming Language :: Python :: 3
Requires-Dist: sqlalchemy >=2.0.13
